aztp_client/__init__.py
aztp_client/client.py
aztp_client/common/__init__.py
aztp_client/common/config.py
aztp_client/common/errors.py
aztp_client/common/types.py
aztp_client_python-0.1.0.dist-info/METADATA
aztp_client_python-0.1.0.dist-info/WHEEL
aztp_client_python-0.1.0.dist-info/top_level.txt
aztp_client_python-0.1.0.dist-info/RECORD
